setup.py
./trendvis/__init__.py
./trendvis/gridclass.py
./trendvis/gridwrapper.py
./trendvis/testing.py
./trendvis/version.py
./trendvis/xgrid_ystack.py
./trendvis/ygrid_xstack.py
TrendVis.egg-info/PKG-INFO
TrendVis.egg-info/SOURCES.txt
TrendVis.egg-info/dependency_links.txt
TrendVis.egg-info/not-zip-safe
TrendVis.egg-info/top_level.txt
trendvis/__init__.py
trendvis/gridclass.py
trendvis/gridwrapper.py
trendvis/testing.py
trendvis/version.py
trendvis/xgrid_ystack.py
trendvis/ygrid_xstack.py