Metadata-Version: 1.1
Name: TrendVis
Version: 0.2.1
Summary: Publication-quality data trend visualization
Home-page: UNKNOWN
Author: Mellissa Cross
Author-email: mellissa.cross@gmail.com
License: Modified BSD
Platform: UNKNOWN
Classifier: Development Status :: 4 - Beta
Classifier: Environment :: Console
Classifier: Intended Audience :: Developers
Classifier: Intended Audience :: Science/Research
Classifier: License :: OSI Approved :: BSD License
Classifier: Programming Language :: Python
Classifier: Programming Language :: Python :: 3
Classifier: Topic :: Scientific/Engineering
Classifier: Operating System :: Microsoft :: Windows
Classifier: Operating System :: POSIX
Classifier: Operating System :: Unix
Classifier: Operating System :: MacOS
